Metadata-Version: 1.1
Name: staff-info
Version: 0.1.2
Summary: GUI to manage such staff information as Time Off, Vacation, Salary and Commission changing. This data is recorded to mysql DB.
Home-page: https://github.com/sergii.iukhymchuk83@gmail.com/staff_info
Author: Sergii Iukhymchuk
Author-email: sergii.iukhymchuk83@gmail.com
License: MIT license
Keywords: staff_info
Platform: UNKNOWN
Classifier: Development Status :: 2 - Pre-Alpha
Classifier: Intended Audience :: Developers
Classifier: License :: OSI Approved :: MIT License
Classifier: Natural Language :: English
Classifier: Programming Language :: Python :: 3.5
